llama_index/tools/bing_search/__init__.py
llama_index/tools/bing_search/base.py
llama_index_tools_bing_search-0.4.1.dist-info/METADATA
llama_index_tools_bing_search-0.4.1.dist-info/WHEEL
llama_index_tools_bing_search-0.4.1.dist-info/licenses/LICENSE
llama_index_tools_bing_search-0.4.1.dist-info/RECORD
